{
	"resource": {
		"name": "hdr_color_storage",
		"usage": "frame",
		"set": "SET_HDR_COLOR_STORAGE",
		"allowed_stages": ["rtx_raygen", "compute"],
		"parameters": {
			"hdr_color": {
				"type": "image",
				"sampler": "default",
				"variable": "u_hdr_color_present_storage",
				"binding": "BINDING_SAMPLER_HDR_COLOR_STORAGE",
				"initial_array_size": 9,
				"array_size_definition": "NUM_HDR_COLOR_ARRAY_ELEMENTS"
			},
			"history": {
				"type": "image",
				"sampler": "default",
				"variable": "u_hdr_color_history",
				"binding": "BINDING_SAMPLER_HISTORY_STORAGE",
				"initial_array_size": 9,
				"array_size_definition": "NUM_HISTORY_ARRAY_ELEMENTS"
			}
		}
	}
}